FABulous_bit_gen/__init__.py
FABulous_bit_gen/bit_gen.py
FABulous_bit_gen/custom_exception.py
fabulous_bit_gen-0.1.0.dist-info/licenses/LICENSE
fabulous_bit_gen-0.1.0.dist-info/METADATA
fabulous_bit_gen-0.1.0.dist-info/WHEEL
fabulous_bit_gen-0.1.0.dist-info/entry_points.txt
fabulous_bit_gen-0.1.0.dist-info/top_level.txt
fabulous_bit_gen-0.1.0.dist-info/RECORD
