Metadata-Version: 2.4
Name: FABulous-bit-gen
Version: 0.1.0
Summary: Bitstream generation utilities for FABulous FPGA fabrics
Author-email: "Jing, Nguyen, Bea, Bardia, Dirk" <dirk.koch@manchester.ac.uk>
Project-URL: Repository, https://github.com/FPGA-Research/FABulous
Project-URL: Documentation, https://fabulous.readthedocs.io
Classifier: Programming Language :: Python :: 3
Classifier: License :: OSI Approved :: Apache Software License
Classifier: Operating System :: OS Independent
Requires-Python: >=3.12
License-File: LICENSE
Requires-Dist: loguru>=0.7.0
Requires-Dist: fasm>=0.0.2
Dynamic: license-file
